{
  "updated_at": "2026-06-12T09:30:47.278545+09:00",
  "season": 2025,
  "source": "npb.jp",
  "teams": {
    "阪神": {
      "batting": {
        "avg": 0.248,
        "ops": 0.712,
        "slg": 0.385,
        "obp": 0.327,
        "hr": 52,
        "runs": 268,
        "wrc_plus_est": 104
      },
      "pitching": {
        "era": 3.21,
        "whip": 1.18,
        "k9": 8.2,
        "bb9": 2.8,
        "saves": 18,
        "holds": 42
      },
      "defense": {
        "fielding_pct": 0.988,
        "errors": 22
      },
      "record": {
        "w": 42,
        "l": 34,
        "t": 2,
        "win_pct": 0.553
      },
      "last_5_record": "3-2",
      "last_10_record": "6-4",
      "last_20_record": "12-8",
      "stadium": "甲子園"
    },
    "巨人": {
      "batting": {
        "avg": 0.258,
        "ops": 0.735,
        "slg": 0.4,
        "obp": 0.335,
        "hr": 68,
        "runs": 298,
        "wrc_plus_est": 108
      },
      "pitching": {
        "era": 3.45,
        "whip": 1.24,
        "k9": 7.8,
        "bb9": 3.0,
        "saves": 20,
        "holds": 38
      },
      "defense": {
        "fielding_pct": 0.984,
        "errors": 28
      },
      "record": {
        "w": 40,
        "l": 36,
        "t": 2,
        "win_pct": 0.526
      },
      "last_5_record": "3-2",
      "last_10_record": "5-5",
      "last_20_record": "11-9",
      "stadium": "東京ドーム"
    },
    "DeNA": {
      "batting": {
        "avg": 0.262,
        "ops": 0.748,
        "slg": 0.412,
        "obp": 0.336,
        "hr": 72,
        "runs": 305,
        "wrc_plus_est": 110
      },
      "pitching": {
        "era": 3.82,
        "whip": 1.32,
        "k9": 7.5,
        "bb9": 3.2,
        "saves": 15,
        "holds": 35
      },
      "defense": {
        "fielding_pct": 0.982,
        "errors": 32
      },
      "record": {
        "w": 6,
        "l": 0,
        "t": 0,
        "win_pct": 0.5
      },
      "last_5_record": "2-3",
      "last_10_record": "5-5",
      "last_20_record": "10-10",
      "stadium": "横浜スタジアム"
    },
    "中日": {
      "batting": {
        "avg": 0.242,
        "ops": 0.681,
        "slg": 0.358,
        "obp": 0.323,
        "hr": 38,
        "runs": 228,
        "wrc_plus_est": 100
      },
      "pitching": {
        "era": 3.55,
        "whip": 1.22,
        "k9": 8.0,
        "bb9": 3.0,
        "saves": 16,
        "holds": 36
      },
      "defense": {
        "fielding_pct": 0.985,
        "errors": 26
      },
      "record": {
        "w": 34,
        "l": 42,
        "t": 2,
        "win_pct": 0.447
      },
      "last_5_record": "2-3",
      "last_10_record": "4-6",
      "last_20_record": "8-12",
      "stadium": "ナゴヤドーム"
    },
    "ヤクルト": {
      "batting": {
        "avg": 0.245,
        "ops": 0.705,
        "slg": 0.372,
        "obp": 0.333,
        "hr": 55,
        "runs": 242,
        "wrc_plus_est": 103
      },
      "pitching": {
        "era": 4.12,
        "whip": 1.38,
        "k9": 7.2,
        "bb9": 3.5,
        "saves": 12,
        "holds": 28
      },
      "defense": {
        "fielding_pct": 0.98,
        "errors": 38
      },
      "record": {
        "w": 7,
        "l": 0,
        "t": 0,
        "win_pct": 0.5
      },
      "last_5_record": "2-3",
      "last_10_record": "4-6",
      "last_20_record": "8-12",
      "stadium": "神宮球場"
    },
    "広島": {
      "batting": {
        "avg": 0.252,
        "ops": 0.71,
        "slg": 0.378,
        "obp": 0.332,
        "hr": 48,
        "runs": 258,
        "wrc_plus_est": 104
      },
      "pitching": {
        "era": 3.68,
        "whip": 1.28,
        "k9": 7.9,
        "bb9": 3.1,
        "saves": 14,
        "holds": 32
      },
      "defense": {
        "fielding_pct": 0.983,
        "errors": 30
      },
      "record": {
        "w": 36,
        "l": 40,
        "t": 2,
        "win_pct": 0.474
      },
      "last_5_record": "2-3",
      "last_10_record": "5-5",
      "last_20_record": "9-11",
      "stadium": "マツダスタジアム"
    },
    "ソフトバンク": {
      "batting": {
        "avg": 0.268,
        "ops": 0.755,
        "slg": 0.418,
        "obp": 0.337,
        "hr": 78,
        "runs": 322,
        "wrc_plus_est": 111
      },
      "pitching": {
        "era": 3.15,
        "whip": 1.16,
        "k9": 8.5,
        "bb9": 2.7,
        "saves": 22,
        "holds": 45
      },
      "defense": {
        "fielding_pct": 0.989,
        "errors": 20
      },
      "record": {
        "w": 4,
        "l": 0,
        "t": 0,
        "win_pct": 0.5
      },
      "last_5_record": "4-1",
      "last_10_record": "7-3",
      "last_20_record": "13-7",
      "stadium": "PayPayドーム"
    },
    "日本ハム": {
      "batting": {
        "avg": 0.255,
        "ops": 0.725,
        "slg": 0.392,
        "obp": 0.333,
        "hr": 62,
        "runs": 275,
        "wrc_plus_est": 106
      },
      "pitching": {
        "era": 3.62,
        "whip": 1.25,
        "k9": 7.9,
        "bb9": 3.0,
        "saves": 17,
        "holds": 36
      },
      "defense": {
        "fielding_pct": 0.984,
        "errors": 28
      },
      "record": {
        "w": 3,
        "l": 0,
        "t": 0,
        "win_pct": 0.5
      },
      "last_5_record": "3-2",
      "last_10_record": "5-5",
      "last_20_record": "10-10",
      "stadium": "エスコンフィールドHOKKAIDO"
    },
    "ロッテ": {
      "batting": {
        "avg": 0.248,
        "ops": 0.712,
        "slg": 0.382,
        "obp": 0.33,
        "hr": 54,
        "runs": 258,
        "wrc_plus_est": 104
      },
      "pitching": {
        "era": 3.72,
        "whip": 1.28,
        "k9": 7.8,
        "bb9": 3.2,
        "saves": 16,
        "holds": 34
      },
      "defense": {
        "fielding_pct": 0.983,
        "errors": 30
      },
      "record": {
        "w": 3,
        "l": 0,
        "t": 0,
        "win_pct": 0.5
      },
      "last_5_record": "3-2",
      "last_10_record": "5-5",
      "last_20_record": "10-10",
      "stadium": "ZOZOマリン"
    },
    "西武": {
      "batting": {
        "avg": 0.24,
        "ops": 0.698,
        "slg": 0.368,
        "obp": 0.33,
        "hr": 45,
        "runs": 238,
        "wrc_plus_est": 102
      },
      "pitching": {
        "era": 4.05,
        "whip": 1.36,
        "k9": 7.3,
        "bb9": 3.4,
        "saves": 14,
        "holds": 30
      },
      "defense": {
        "fielding_pct": 0.981,
        "errors": 35
      },
      "record": {
        "w": 33,
        "l": 43,
        "t": 2,
        "win_pct": 0.434
      },
      "last_5_record": "2-3",
      "last_10_record": "4-6",
      "last_20_record": "8-12",
      "stadium": "ベルーナドーム"
    },
    "楽天": {
      "batting": {
        "avg": 0.255,
        "ops": 0.72,
        "slg": 0.39,
        "obp": 0.33,
        "hr": 60,
        "runs": 265,
        "wrc_plus_est": 106
      },
      "pitching": {
        "era": 3.85,
        "whip": 1.3,
        "k9": 7.5,
        "bb9": 3.3,
        "saves": 15,
        "holds": 32
      },
      "defense": {
        "fielding_pct": 0.982,
        "errors": 32
      },
      "record": {
        "w": 36,
        "l": 40,
        "t": 2,
        "win_pct": 0.474
      },
      "last_5_record": "2-3",
      "last_10_record": "5-5",
      "last_20_record": "9-11",
      "stadium": "楽天生命パーク宮城"
    },
    "オリックス": {
      "batting": {
        "avg": 0.252,
        "ops": 0.718,
        "slg": 0.388,
        "obp": 0.33,
        "hr": 58,
        "runs": 272,
        "wrc_plus_est": 105
      },
      "pitching": {
        "era": 3.28,
        "whip": 1.2,
        "k9": 8.1,
        "bb9": 2.9,
        "saves": 18,
        "holds": 40
      },
      "defense": {
        "fielding_pct": 0.985,
        "errors": 26
      },
      "record": {
        "w": 3,
        "l": 0,
        "t": 0,
        "win_pct": 0.5
      },
      "last_5_record": "3-2",
      "last_10_record": "6-4",
      "last_20_record": "11-9",
      "stadium": "京セラドーム大阪"
    }
  },
  "pitchers": {
    "阪神": [
      {
        "name": "才木浩人",
        "era": 2.15,
        "whip": 0.92,
        "fip_est": 2.45,
        "k9": 10.2,
        "bb9": 1.8,
        "ip": 105.0,
        "games": 17,
        "wins": 9,
        "losses": 3,
        "handedness": "R"
      },
      {
        "name": "西勇輝",
        "era": 2.88,
        "whip": 1.08,
        "fip_est": 2.95,
        "k9": 7.5,
        "bb9": 2.2,
        "ip": 88.0,
        "games": 15,
        "wins": 7,
        "losses": 4,
        "handedness": "R"
      },
      {
        "name": "大竹耕太郎",
        "era": 3.12,
        "whip": 1.15,
        "fip_est": 3.2,
        "k9": 7.8,
        "bb9": 2.5,
        "ip": 75.0,
        "games": 13,
        "wins": 5,
        "losses": 4,
        "handedness": "L"
      }
    ],
    "巨人": [
      {
        "name": "戸郷翔征",
        "era": 2.42,
        "whip": 0.98,
        "fip_est": 2.6,
        "k9": 9.8,
        "bb9": 2.0,
        "ip": 112.0,
        "games": 18,
        "wins": 10,
        "losses": 4,
        "handedness": "R"
      },
      {
        "name": "菅野智之",
        "era": 3.05,
        "whip": 1.12,
        "fip_est": 3.15,
        "k9": 8.2,
        "bb9": 2.3,
        "ip": 92.0,
        "games": 16,
        "wins": 7,
        "losses": 5,
        "handedness": "R"
      },
      {
        "name": "山﨑伊織",
        "era": 3.38,
        "whip": 1.2,
        "fip_est": 3.45,
        "k9": 8.5,
        "bb9": 2.8,
        "ip": 80.0,
        "games": 14,
        "wins": 6,
        "losses": 5,
        "handedness": "R"
      }
    ],
    "DeNA": [
      {
        "name": "東克樹",
        "era": 2.68,
        "whip": 1.05,
        "fip_est": 2.8,
        "k9": 8.8,
        "bb9": 2.2,
        "ip": 98.0,
        "games": 16,
        "wins": 8,
        "losses": 4,
        "handedness": "L"
      },
      {
        "name": "バウアー",
        "era": 3.15,
        "whip": 1.18,
        "fip_est": 3.2,
        "k9": 9.2,
        "bb9": 2.8,
        "ip": 85.0,
        "games": 15,
        "wins": 6,
        "losses": 5,
        "handedness": "R"
      },
      {
        "name": "今永昇太",
        "era": 2.88,
        "whip": 1.08,
        "fip_est": 2.95,
        "k9": 9.5,
        "bb9": 2.2,
        "ip": 45.0,
        "games": 8,
        "wins": 4,
        "losses": 2,
        "handedness": "L"
      }
    ],
    "中日": [
      {
        "name": "小笠原慎之介",
        "era": 2.88,
        "whip": 1.1,
        "fip_est": 2.98,
        "k9": 8.5,
        "bb9": 2.5,
        "ip": 90.0,
        "games": 15,
        "wins": 7,
        "losses": 4,
        "handedness": "L"
      },
      {
        "name": "柳裕也",
        "era": 3.42,
        "whip": 1.22,
        "fip_est": 3.52,
        "k9": 7.5,
        "bb9": 3.0,
        "ip": 78.0,
        "games": 13,
        "wins": 5,
        "losses": 5,
        "handedness": "R"
      },
      {
        "name": "涌井秀章",
        "era": 3.68,
        "whip": 1.28,
        "fip_est": 3.78,
        "k9": 6.8,
        "bb9": 2.8,
        "ip": 68.0,
        "games": 12,
        "wins": 4,
        "losses": 5,
        "handedness": "R"
      }
    ],
    "ヤクルト": [
      {
        "name": "小川泰弘",
        "era": 3.42,
        "whip": 1.22,
        "fip_est": 3.52,
        "k9": 7.2,
        "bb9": 2.8,
        "ip": 82.0,
        "games": 14,
        "wins": 5,
        "losses": 6,
        "handedness": "R"
      },
      {
        "name": "石川雅規",
        "era": 3.85,
        "whip": 1.3,
        "fip_est": 3.95,
        "k9": 6.5,
        "bb9": 2.5,
        "ip": 72.0,
        "games": 13,
        "wins": 4,
        "losses": 6,
        "handedness": "L"
      },
      {
        "name": "金久保優斗",
        "era": 4.12,
        "whip": 1.38,
        "fip_est": 4.22,
        "k9": 7.0,
        "bb9": 3.5,
        "ip": 60.0,
        "games": 11,
        "wins": 3,
        "losses": 6,
        "handedness": "R"
      }
    ],
    "広島": [
      {
        "name": "九里亜蓮",
        "era": 2.95,
        "whip": 1.12,
        "fip_est": 3.05,
        "k9": 7.8,
        "bb9": 2.5,
        "ip": 95.0,
        "games": 16,
        "wins": 7,
        "losses": 5,
        "handedness": "R"
      },
      {
        "name": "床田寛樹",
        "era": 3.22,
        "whip": 1.18,
        "fip_est": 3.3,
        "k9": 7.5,
        "bb9": 2.6,
        "ip": 85.0,
        "games": 14,
        "wins": 6,
        "losses": 5,
        "handedness": "L"
      },
      {
        "name": "玉村昇悟",
        "era": 3.55,
        "whip": 1.25,
        "fip_est": 3.65,
        "k9": 7.2,
        "bb9": 3.0,
        "ip": 70.0,
        "games": 12,
        "wins": 5,
        "losses": 5,
        "handedness": "L"
      }
    ],
    "ソフトバンク": [
      {
        "name": "有原航平",
        "era": 2.28,
        "whip": 0.95,
        "fip_est": 2.4,
        "k9": 9.5,
        "bb9": 2.0,
        "ip": 118.0,
        "games": 19,
        "wins": 11,
        "losses": 3,
        "handedness": "R"
      },
      {
        "name": "石川柊太",
        "era": 2.78,
        "whip": 1.05,
        "fip_est": 2.88,
        "k9": 8.8,
        "bb9": 2.2,
        "ip": 98.0,
        "games": 16,
        "wins": 8,
        "losses": 4,
        "handedness": "R"
      },
      {
        "name": "モイネロ",
        "era": 2.45,
        "whip": 1.02,
        "fip_est": 2.55,
        "k9": 9.2,
        "bb9": 2.5,
        "ip": 82.0,
        "games": 14,
        "wins": 7,
        "losses": 3,
        "handedness": "L"
      }
    ],
    "日本ハム": [
      {
        "name": "上沢直之",
        "era": 2.88,
        "whip": 1.08,
        "fip_est": 2.98,
        "k9": 8.2,
        "bb9": 2.2,
        "ip": 95.0,
        "games": 16,
        "wins": 7,
        "losses": 4,
        "handedness": "R"
      },
      {
        "name": "加藤貴之",
        "era": 3.12,
        "whip": 1.15,
        "fip_est": 3.22,
        "k9": 7.8,
        "bb9": 2.5,
        "ip": 85.0,
        "games": 14,
        "wins": 6,
        "losses": 5,
        "handedness": "L"
      },
      {
        "name": "金村尚真",
        "era": 3.45,
        "whip": 1.22,
        "fip_est": 3.55,
        "k9": 8.0,
        "bb9": 2.8,
        "ip": 75.0,
        "games": 13,
        "wins": 5,
        "losses": 5,
        "handedness": "R"
      }
    ],
    "ロッテ": [
      {
        "name": "佐々木朗希",
        "era": 1.88,
        "whip": 0.82,
        "fip_est": 1.98,
        "k9": 12.5,
        "bb9": 1.5,
        "ip": 72.0,
        "games": 12,
        "wins": 6,
        "losses": 2,
        "handedness": "R"
      },
      {
        "name": "種市篤暉",
        "era": 3.02,
        "whip": 1.12,
        "fip_est": 3.12,
        "k9": 8.2,
        "bb9": 2.5,
        "ip": 90.0,
        "games": 15,
        "wins": 6,
        "losses": 5,
        "handedness": "R"
      },
      {
        "name": "小島和哉",
        "era": 3.45,
        "whip": 1.22,
        "fip_est": 3.55,
        "k9": 7.5,
        "bb9": 2.8,
        "ip": 78.0,
        "games": 13,
        "wins": 5,
        "losses": 5,
        "handedness": "L"
      }
    ],
    "西武": [
      {
        "name": "今井達也",
        "era": 3.42,
        "whip": 1.22,
        "fip_est": 3.52,
        "k9": 8.2,
        "bb9": 3.0,
        "ip": 85.0,
        "games": 14,
        "wins": 5,
        "losses": 6,
        "handedness": "R"
      },
      {
        "name": "高橋光成",
        "era": 3.68,
        "whip": 1.28,
        "fip_est": 3.78,
        "k9": 7.8,
        "bb9": 3.2,
        "ip": 78.0,
        "games": 13,
        "wins": 4,
        "losses": 6,
        "handedness": "R"
      },
      {
        "name": "松本航",
        "era": 3.95,
        "whip": 1.32,
        "fip_est": 4.05,
        "k9": 7.2,
        "bb9": 3.0,
        "ip": 68.0,
        "games": 12,
        "wins": 4,
        "losses": 5,
        "handedness": "R"
      }
    ],
    "楽天": [
      {
        "name": "田中将大",
        "era": 3.12,
        "whip": 1.18,
        "fip_est": 3.22,
        "k9": 7.8,
        "bb9": 2.5,
        "ip": 88.0,
        "games": 15,
        "wins": 6,
        "losses": 5,
        "handedness": "R"
      },
      {
        "name": "岸孝之",
        "era": 3.38,
        "whip": 1.22,
        "fip_est": 3.48,
        "k9": 7.5,
        "bb9": 2.5,
        "ip": 78.0,
        "games": 13,
        "wins": 5,
        "losses": 5,
        "handedness": "R"
      },
      {
        "name": "早川隆久",
        "era": 3.25,
        "whip": 1.18,
        "fip_est": 3.35,
        "k9": 8.0,
        "bb9": 2.8,
        "ip": 82.0,
        "games": 14,
        "wins": 6,
        "losses": 5,
        "handedness": "L"
      }
    ],
    "オリックス": [
      {
        "name": "山下舜平大",
        "era": 2.42,
        "whip": 0.98,
        "fip_est": 2.52,
        "k9": 9.8,
        "bb9": 1.8,
        "ip": 108.0,
        "games": 17,
        "wins": 9,
        "losses": 3,
        "handedness": "R"
      },
      {
        "name": "宮城大弥",
        "era": 2.88,
        "whip": 1.08,
        "fip_est": 2.98,
        "k9": 8.5,
        "bb9": 2.2,
        "ip": 92.0,
        "games": 15,
        "wins": 7,
        "losses": 4,
        "handedness": "L"
      },
      {
        "name": "田嶋大樹",
        "era": 3.18,
        "whip": 1.15,
        "fip_est": 3.28,
        "k9": 8.0,
        "bb9": 2.5,
        "ip": 78.0,
        "games": 13,
        "wins": 6,
        "losses": 4,
        "handedness": "L"
      }
    ]
  },
  "bullpens": {
    "阪神": {
      "era": 2.88,
      "saves": 18,
      "blown_saves": 2,
      "holds": 42
    },
    "巨人": {
      "era": 3.12,
      "saves": 20,
      "blown_saves": 3,
      "holds": 38
    },
    "DeNA": {
      "era": 3.52,
      "saves": 15,
      "blown_saves": 4,
      "holds": 35
    },
    "中日": {
      "era": 3.22,
      "saves": 16,
      "blown_saves": 3,
      "holds": 36
    },
    "ヤクルト": {
      "era": 3.85,
      "saves": 12,
      "blown_saves": 5,
      "holds": 28
    },
    "広島": {
      "era": 3.35,
      "saves": 14,
      "blown_saves": 3,
      "holds": 32
    },
    "ソフトバンク": {
      "era": 2.72,
      "saves": 22,
      "blown_saves": 2,
      "holds": 45
    },
    "日本ハム": {
      "era": 3.28,
      "saves": 17,
      "blown_saves": 3,
      "holds": 36
    },
    "ロッテ": {
      "era": 3.38,
      "saves": 16,
      "blown_saves": 3,
      "holds": 34
    },
    "西武": {
      "era": 3.72,
      "saves": 14,
      "blown_saves": 4,
      "holds": 30
    },
    "楽天": {
      "era": 3.52,
      "saves": 15,
      "blown_saves": 4,
      "holds": 32
    },
    "オリックス": {
      "era": 2.98,
      "saves": 18,
      "blown_saves": 2,
      "holds": 40
    }
  }
}